beastiary/__init__.py
beastiary/api/__init__.py
beastiary/api/core.py
beastiary/api/deps.py
beastiary/api/endpoints/__init__.py
beastiary/api/endpoints/explorer.py
beastiary/api/endpoints/traces.py
beastiary/api/main.py
beastiary/cli.py
beastiary/crud/__init__.py
beastiary/crud/base.py
beastiary/crud/crud_sample.py
beastiary/crud/crud_trace.py
beastiary/db/__init__.py
beastiary/db/database.py
beastiary/log.py
beastiary/schemas/__init__.py
beastiary/schemas/sample.py
beastiary/schemas/trace.py
beastiary/webapp-dist/android-chrome-192x192.png
beastiary/webapp-dist/android-chrome-512x512.png
beastiary/webapp-dist/apple-touch-icon.png
beastiary/webapp-dist/css/chunk-vendors.91bba9cc.css
beastiary/webapp-dist/css/login.e537a9fa.css
beastiary/webapp-dist/css/login~main-dashboard.f3d66085.css
beastiary/webapp-dist/css/login~main~main-dashboard.31439c1e.css
beastiary/webapp-dist/css/main-dashboard.e2aaff73.css
beastiary/webapp-dist/css/main.f21905bc.css
beastiary/webapp-dist/css/main~main-dashboard.00152d94.css
beastiary/webapp-dist/favicon-16x16.png
beastiary/webapp-dist/favicon-32x32.png
beastiary/webapp-dist/favicon.ico
beastiary/webapp-dist/index.html
beastiary/webapp-dist/js/app.ae01b4f2.js
beastiary/webapp-dist/js/app.ae01b4f2.js.map
beastiary/webapp-dist/js/chunk-vendors.afbd1421.js
beastiary/webapp-dist/js/chunk-vendors.afbd1421.js.map
beastiary/webapp-dist/js/login.a133ba4e.js
beastiary/webapp-dist/js/login.a133ba4e.js.map
beastiary/webapp-dist/js/login~main-dashboard.ada10ab4.js
beastiary/webapp-dist/js/login~main-dashboard.ada10ab4.js.map
beastiary/webapp-dist/js/login~main~main-dashboard.fe81a9da.js
beastiary/webapp-dist/js/login~main~main-dashboard.fe81a9da.js.map
beastiary/webapp-dist/js/main-dashboard.1aa0cef9.js
beastiary/webapp-dist/js/main-dashboard.1aa0cef9.js.map
beastiary/webapp-dist/js/main.6e01feb4.js
beastiary/webapp-dist/js/main.6e01feb4.js.map
beastiary/webapp-dist/js/main~main-dashboard.52fc0832.js
beastiary-1.8.3.dist-info/METADATA
beastiary-1.8.3.dist-info/WHEEL
beastiary-1.8.3.dist-info/entry_points.txt
beastiary-1.8.3.dist-info/RECORD
