Metadata-Version: 2.1
Name: beastiary
Version: 1.8.3
Summary: Real time and remote MCMC trace monitoring with BEASTIARY
Author: Wytamma Wirth
Author-email: wytamma.wirth@me.com
Requires-Python: >=3.8,<4.0
Classifier: Programming Language :: Python :: 3
Classifier: Programming Language :: Python :: 3.8
Classifier: Programming Language :: Python :: 3.9
Classifier: Programming Language :: Python :: 3.10
Classifier: Programming Language :: Python :: 3.11
Classifier: Programming Language :: Python :: 3.12
Requires-Dist: aiofiles (<0.6.0)
Requires-Dist: fastapi[all] (>=0.95.1,<0.96.0)
Requires-Dist: typer[all] (>=0.3.2,<0.4.0)
Requires-Dist: with-cloudflared (>=0.1.0,<0.2.0)
